loler_spider/HeroSpider.py
loler_spider/__init__.py
loler_spider-1.0.1.dist-info/LICENSE
loler_spider-1.0.1.dist-info/METADATA
loler_spider-1.0.1.dist-info/WHEEL
loler_spider-1.0.1.dist-info/top_level.txt
loler_spider-1.0.1.dist-info/RECORD
