Metadata-Version: 2.1
Name: loler-spider
Version: 1.0.1
Summary: A spider to download lol-hero image
Home-page: https://github.com/zzzzls/
Author: zzzzls
Author-email: 245129129@qq.com
License: MIT
Keywords: lol,image,spider,download
Platform: UNKNOWN
Requires-Dist: requests
Requires-Dist: tqdm
